{
  "annotations": {
    "list": [
      {
        "builtIn": 1,
        "datasource": {
          "type": "grafana",
          "uid": "-- Grafana --"
        },
        "enable": true,
        "hide": true,
        "iconColor": "rgba(0, 211, 255, 1)",
        "name": "Annotations & Alerts",
        "target": {
          "limit": 100,
          "matchAny": false,
          "tags": [],
          "type": "dashboard"
        },
        "type": "dashboard"
      }
    ]
  },
  "editable": true,
  "fiscalYearStartMonth": 0,
  "graphTooltip": 2,
  "id": 6,
  "links": [],
  "liveNow": false,
  "panels": [
    {
      "datasource": {
        "type": "prometheus",
        "uid": "MWzG0Bc4k"
      },
      "fieldConfig": {
        "defaults": {
          "color": {
            "mode": "palette-classic"
          },
          "custom": {
            "axisLabel": "",
            "axisPlacement": "auto",
            "barAlignment": 0,
            "drawStyle": "line",
            "fillOpacity": 10,
            "gradientMode": "none",
            "hideFrom": {
              "legend": false,
              "tooltip": false,
              "viz": false
            },
            "lineInterpolation": "linear",
            "lineWidth": 2,
            "pointSize": 5,
            "scaleDistribution": {
              "type": "linear"
            },
            "showPoints": "never",
            "spanNulls": true,
            "stacking": {
              "group": "A",
              "mode": "none"
            },
            "thresholdsStyle": {
              "mode": "off"
            }
          },
          "mappings": [],
          "thresholds": {
            "mode": "absolute",
            "steps": [
              {
                "color": "green",
                "value": null
              },
              {
                "color": "red",
                "value": 80
              }
            ]
          },
          "unit": "reqps"
        },
        "overrides": [
          {
            "matcher": {
              "id": "byName",
              "options": "400"
            },
            "properties": [
              {
                "id": "color",
                "value": {
                  "fixedColor": "dark-orange",
                  "mode": "fixed"
                }
              }
            ]
          },
          {
            "matcher": {
              "id": "byName",
              "options": "500"
            },
            "properties": [
              {
                "id": "color",
                "value": {
                  "fixedColor": "dark-red",
                  "mode": "fixed"
                }
              }
            ]
          }
        ]
      },
      "gridPos": {
        "h": 9,
        "w": 24,
        "x": 0,
        "y": 0
      },
      "id": 16,
      "links": [],
      "options": {
        "legend": {
          "calcs": ["mean"],
          "displayMode": "list",
          "placement": "bottom"
        },
        "tooltip": {
          "mode": "multi",
          "sort": "desc"
        }
      },
      "pluginVersion": "9.0.4",
      "repeatDirection": "h",
      "targets": [
        {
          "datasource": {
            "type": "prometheus",
            "uid": "MWzG0Bc4k"
          },
          "editorMode": "code",
          "expr": "sum(rate(nginx_ingress_controller_requests{ingress=\"apigateway\", namespace=\"army\", status=~\"2.+\"}[15m]))",
          "format": "time_series",
          "hide": false,
          "instant": false,
          "interval": "",
          "intervalFactor": 1,
          "legendFormat": "200",
          "metric": "network",
          "refId": "A",
          "step": 10
        },
        {
          "datasource": {
            "type": "prometheus",
            "uid": "MWzG0Bc4k"
          },
          "editorMode": "code",
          "expr": "sum(rate(nginx_ingress_controller_requests{ingress=\"apigateway\", namespace=\"army\", status=~\"4.+\"}[15m]))",
          "hide": false,
          "legendFormat": "400",
          "range": true,
          "refId": "B"
        },
        {
          "datasource": {
            "type": "prometheus",
            "uid": "MWzG0Bc4k"
          },
          "editorMode": "code",
          "expr": "sum(rate(nginx_ingress_controller_requests{ingress=\"apigateway\", namespace=\"army\", status=~\"5.+\"}[15m]))",
          "hide": false,
          "legendFormat": "500",
          "range": true,
          "refId": "C"
        }
      ],
      "title": "Ingress Request Volume",
      "type": "timeseries"
    },
    {
      "datasource": {
        "type": "prometheus",
        "uid": "MWzG0Bc4k"
      },
      "fieldConfig": {
        "defaults": {
          "color": {
            "mode": "palette-classic"
          },
          "custom": {
            "axisLabel": "",
            "axisPlacement": "auto",
            "barAlignment": 0,
            "drawStyle": "line",
            "fillOpacity": 0,
            "gradientMode": "none",
            "hideFrom": {
              "legend": false,
              "tooltip": false,
              "viz": false
            },
            "lineInterpolation": "linear",
            "lineWidth": 1,
            "pointSize": 5,
            "scaleDistribution": {
              "type": "linear"
            },
            "showPoints": "auto",
            "spanNulls": false,
            "stacking": {
              "group": "A",
              "mode": "none"
            },
            "thresholdsStyle": {
              "mode": "off"
            }
          },
          "mappings": [],
          "thresholds": {
            "mode": "absolute",
            "steps": [
              {
                "color": "green",
                "value": null
              },
              {
                "color": "red",
                "value": 80
              }
            ]
          },
          "unit": "percentunit"
        },
        "overrides": [
          {
            "matcher": {
              "id": "byName",
              "options": "limit"
            },
            "properties": [
              {
                "id": "color",
                "value": {
                  "fixedColor": "semi-dark-red",
                  "mode": "fixed"
                }
              }
            ]
          },
          {
            "matcher": {
              "id": "byName",
              "options": "request"
            },
            "properties": [
              {
                "id": "color",
                "value": {
                  "fixedColor": "semi-dark-orange",
                  "mode": "fixed"
                }
              }
            ]
          },
          {
            "matcher": {
              "id": "byName",
              "options": "avg"
            },
            "properties": [
              {
                "id": "color",
                "value": {
                  "fixedColor": "semi-dark-green",
                  "mode": "fixed"
                }
              }
            ]
          }
        ]
      },
      "gridPos": {
        "h": 9,
        "w": 12,
        "x": 0,
        "y": 9
      },
      "id": 7,
      "options": {
        "legend": {
          "calcs": ["mean", "max"],
          "displayMode": "list",
          "placement": "bottom"
        },
        "tooltip": {
          "mode": "single",
          "sort": "none"
        }
      },
      "targets": [
        {
          "datasource": {
            "type": "prometheus",
            "uid": "MWzG0Bc4k"
          },
          "editorMode": "code",
          "expr": "avg(rate(container_cpu_usage_seconds_total{namespace=\"army\", container=\"cron-scheduler\"}[15m]))",
          "legendFormat": "avg",
          "range": true,
          "refId": "A"
        },
        {
          "datasource": {
            "type": "prometheus",
            "uid": "MWzG0Bc4k"
          },
          "editorMode": "code",
          "expr": "max(kube_pod_container_resource_requests{namespace=\"army\", container=\"cron-scheduler\", resource=\"cpu\"})",
          "hide": false,
          "legendFormat": "request",
          "range": true,
          "refId": "B"
        },
        {
          "datasource": {
            "type": "prometheus",
            "uid": "MWzG0Bc4k"
          },
          "editorMode": "code",
          "expr": "max(kube_pod_container_resource_limits{namespace=\"army\", container=\"cron-scheduler\", resource=\"cpu\"})",
          "hide": false,
          "legendFormat": "limit",
          "range": true,
          "refId": "C"
        }
      ],
      "title": "CPU usage (cron-scheduler)",
      "type": "timeseries"
    },
    {
      "datasource": {
        "type": "prometheus",
        "uid": "MWzG0Bc4k"
      },
      "fieldConfig": {
        "defaults": {
          "color": {
            "mode": "palette-classic"
          },
          "custom": {
            "axisLabel": "",
            "axisPlacement": "auto",
            "barAlignment": 0,
            "drawStyle": "line",
            "fillOpacity": 0,
            "gradientMode": "none",
            "hideFrom": {
              "legend": false,
              "tooltip": false,
              "viz": false
            },
            "lineInterpolation": "linear",
            "lineWidth": 1,
            "pointSize": 5,
            "scaleDistribution": {
              "type": "linear"
            },
            "showPoints": "auto",
            "spanNulls": false,
            "stacking": {
              "group": "A",
              "mode": "none"
            },
            "thresholdsStyle": {
              "mode": "off"
            }
          },
          "mappings": [],
          "thresholds": {
            "mode": "absolute",
            "steps": [
              {
                "color": "green",
                "value": null
              },
              {
                "color": "red",
                "value": 80
              }
            ]
          },
          "unit": "bytes"
        },
        "overrides": [
          {
            "matcher": {
              "id": "byName",
              "options": "limit"
            },
            "properties": [
              {
                "id": "color",
                "value": {
                  "fixedColor": "semi-dark-red",
                  "mode": "fixed"
                }
              }
            ]
          },
          {
            "matcher": {
              "id": "byName",
              "options": "request"
            },
            "properties": [
              {
                "id": "color",
                "value": {
                  "fixedColor": "semi-dark-orange",
                  "mode": "fixed"
                }
              }
            ]
          },
          {
            "matcher": {
              "id": "byName",
              "options": "avg"
            },
            "properties": [
              {
                "id": "color",
                "value": {
                  "fixedColor": "semi-dark-green",
                  "mode": "fixed"
                }
              }
            ]
          }
        ]
      },
      "gridPos": {
        "h": 9,
        "w": 12,
        "x": 12,
        "y": 9
      },
      "id": 10,
      "options": {
        "legend": {
          "calcs": ["mean", "max"],
          "displayMode": "list",
          "placement": "bottom"
        },
        "tooltip": {
          "mode": "single",
          "sort": "none"
        }
      },
      "targets": [
        {
          "datasource": {
            "type": "prometheus",
            "uid": "MWzG0Bc4k"
          },
          "editorMode": "code",
          "expr": "avg(container_memory_usage_bytes{namespace=\"army\", container=\"cron-scheduler\"})",
          "legendFormat": "avg",
          "range": true,
          "refId": "A"
        },
        {
          "datasource": {
            "type": "prometheus",
            "uid": "MWzG0Bc4k"
          },
          "editorMode": "code",
          "expr": "max(kube_pod_container_resource_requests{namespace=\"army\", container=\"cron-scheduler\", resource=\"memory\"})",
          "hide": false,
          "legendFormat": "request",
          "range": true,
          "refId": "B"
        },
        {
          "datasource": {
            "type": "prometheus",
            "uid": "MWzG0Bc4k"
          },
          "editorMode": "code",
          "expr": "max(kube_pod_container_resource_limits{namespace=\"army\", container=\"cron-scheduler\", resource=\"memory\"})",
          "hide": false,
          "legendFormat": "limit",
          "range": true,
          "refId": "C"
        }
      ],
      "title": "Memory usage (cron-scheduler)",
      "type": "timeseries"
    },
    {
      "datasource": {
        "type": "prometheus",
        "uid": "MWzG0Bc4k"
      },
      "fieldConfig": {
        "defaults": {
          "color": {
            "mode": "palette-classic"
          },
          "custom": {
            "axisLabel": "",
            "axisPlacement": "auto",
            "barAlignment": 0,
            "drawStyle": "line",
            "fillOpacity": 0,
            "gradientMode": "none",
            "hideFrom": {
              "legend": false,
              "tooltip": false,
              "viz": false
            },
            "lineInterpolation": "linear",
            "lineWidth": 1,
            "pointSize": 5,
            "scaleDistribution": {
              "type": "linear"
            },
            "showPoints": "auto",
            "spanNulls": false,
            "stacking": {
              "group": "A",
              "mode": "none"
            },
            "thresholdsStyle": {
              "mode": "off"
            }
          },
          "mappings": [],
          "thresholds": {
            "mode": "absolute",
            "steps": [
              {
                "color": "green"
              },
              {
                "color": "red",
                "value": 80
              }
            ]
          },
          "unit": "percentunit"
        },
        "overrides": [
          {
            "matcher": {
              "id": "byName",
              "options": "limit"
            },
            "properties": [
              {
                "id": "color",
                "value": {
                  "fixedColor": "semi-dark-red",
                  "mode": "fixed"
                }
              }
            ]
          },
          {
            "matcher": {
              "id": "byName",
              "options": "request"
            },
            "properties": [
              {
                "id": "color",
                "value": {
                  "fixedColor": "semi-dark-orange",
                  "mode": "fixed"
                }
              }
            ]
          },
          {
            "matcher": {
              "id": "byName",
              "options": "avg"
            },
            "properties": [
              {
                "id": "color",
                "value": {
                  "fixedColor": "semi-dark-green",
                  "mode": "fixed"
                }
              }
            ]
          }
        ]
      },
      "gridPos": {
        "h": 9,
        "w": 12,
        "x": 0,
        "y": 18
      },
      "id": 8,
      "options": {
        "legend": {
          "calcs": ["mean", "max"],
          "displayMode": "list",
          "placement": "bottom"
        },
        "tooltip": {
          "mode": "single",
          "sort": "none"
        }
      },
      "targets": [
        {
          "datasource": {
            "type": "prometheus",
            "uid": "MWzG0Bc4k"
          },
          "editorMode": "code",
          "expr": "avg(rate(container_cpu_usage_seconds_total{namespace=\"army\", container=\"apigateway\"}[15m]))",
          "legendFormat": "avg",
          "range": true,
          "refId": "A"
        },
        {
          "datasource": {
            "type": "prometheus",
            "uid": "MWzG0Bc4k"
          },
          "editorMode": "code",
          "expr": "max(kube_pod_container_resource_requests{namespace=\"army\", container=\"apigateway\", resource=\"cpu\"})",
          "hide": false,
          "legendFormat": "request",
          "range": true,
          "refId": "B"
        },
        {
          "datasource": {
            "type": "prometheus",
            "uid": "MWzG0Bc4k"
          },
          "editorMode": "code",
          "expr": "max(kube_pod_container_resource_limits{namespace=\"army\", container=\"apigateway\", resource=\"cpu\"})",
          "hide": false,
          "legendFormat": "limit",
          "range": true,
          "refId": "C"
        }
      ],
      "title": "CPU usage (apigateway)",
      "type": "timeseries"
    },
    {
      "datasource": {
        "type": "prometheus",
        "uid": "MWzG0Bc4k"
      },
      "fieldConfig": {
        "defaults": {
          "color": {
            "mode": "palette-classic"
          },
          "custom": {
            "axisLabel": "",
            "axisPlacement": "auto",
            "barAlignment": 0,
            "drawStyle": "line",
            "fillOpacity": 0,
            "gradientMode": "none",
            "hideFrom": {
              "legend": false,
              "tooltip": false,
              "viz": false
            },
            "lineInterpolation": "linear",
            "lineWidth": 1,
            "pointSize": 5,
            "scaleDistribution": {
              "type": "linear"
            },
            "showPoints": "auto",
            "spanNulls": false,
            "stacking": {
              "group": "A",
              "mode": "none"
            },
            "thresholdsStyle": {
              "mode": "off"
            }
          },
          "mappings": [],
          "thresholds": {
            "mode": "absolute",
            "steps": [
              {
                "color": "green"
              },
              {
                "color": "red",
                "value": 80
              }
            ]
          },
          "unit": "bytes"
        },
        "overrides": [
          {
            "matcher": {
              "id": "byName",
              "options": "limit"
            },
            "properties": [
              {
                "id": "color",
                "value": {
                  "fixedColor": "semi-dark-red",
                  "mode": "fixed"
                }
              }
            ]
          },
          {
            "matcher": {
              "id": "byName",
              "options": "request"
            },
            "properties": [
              {
                "id": "color",
                "value": {
                  "fixedColor": "semi-dark-orange",
                  "mode": "fixed"
                }
              }
            ]
          },
          {
            "matcher": {
              "id": "byName",
              "options": "avg"
            },
            "properties": [
              {
                "id": "color",
                "value": {
                  "fixedColor": "semi-dark-green",
                  "mode": "fixed"
                }
              }
            ]
          }
        ]
      },
      "gridPos": {
        "h": 9,
        "w": 12,
        "x": 12,
        "y": 18
      },
      "id": 9,
      "options": {
        "legend": {
          "calcs": ["mean", "max"],
          "displayMode": "list",
          "placement": "bottom"
        },
        "tooltip": {
          "mode": "single",
          "sort": "none"
        }
      },
      "targets": [
        {
          "datasource": {
            "type": "prometheus",
            "uid": "MWzG0Bc4k"
          },
          "editorMode": "code",
          "expr": "avg(container_memory_usage_bytes{namespace=\"army\", container=\"apigateway\"})",
          "legendFormat": "avg",
          "range": true,
          "refId": "A"
        },
        {
          "datasource": {
            "type": "prometheus",
            "uid": "MWzG0Bc4k"
          },
          "editorMode": "code",
          "expr": "max(kube_pod_container_resource_requests{namespace=\"army\", container=\"apigateway\", resource=\"memory\"})",
          "hide": false,
          "legendFormat": "request",
          "range": true,
          "refId": "B"
        },
        {
          "datasource": {
            "type": "prometheus",
            "uid": "MWzG0Bc4k"
          },
          "editorMode": "code",
          "expr": "max(kube_pod_container_resource_limits{namespace=\"army\", container=\"apigateway\", resource=\"memory\"})",
          "hide": false,
          "legendFormat": "limit",
          "range": true,
          "refId": "C"
        }
      ],
      "title": "Memory usage (apigateway)",
      "type": "timeseries"
    },
    {
      "datasource": {
        "type": "prometheus",
        "uid": "MWzG0Bc4k"
      },
      "fieldConfig": {
        "defaults": {
          "color": {
            "mode": "palette-classic"
          },
          "custom": {
            "axisLabel": "",
            "axisPlacement": "auto",
            "barAlignment": 0,
            "drawStyle": "line",
            "fillOpacity": 0,
            "gradientMode": "none",
            "hideFrom": {
              "legend": false,
              "tooltip": false,
              "viz": false
            },
            "lineInterpolation": "linear",
            "lineWidth": 1,
            "pointSize": 5,
            "scaleDistribution": {
              "type": "linear"
            },
            "showPoints": "auto",
            "spanNulls": false,
            "stacking": {
              "group": "A",
              "mode": "none"
            },
            "thresholdsStyle": {
              "mode": "off"
            }
          },
          "mappings": [],
          "thresholds": {
            "mode": "absolute",
            "steps": [
              {
                "color": "green"
              },
              {
                "color": "red",
                "value": 80
              }
            ]
          },
          "unit": "percentunit"
        },
        "overrides": [
          {
            "matcher": {
              "id": "byName",
              "options": "limit"
            },
            "properties": [
              {
                "id": "color",
                "value": {
                  "fixedColor": "semi-dark-red",
                  "mode": "fixed"
                }
              }
            ]
          },
          {
            "matcher": {
              "id": "byName",
              "options": "request"
            },
            "properties": [
              {
                "id": "color",
                "value": {
                  "fixedColor": "semi-dark-orange",
                  "mode": "fixed"
                }
              }
            ]
          },
          {
            "matcher": {
              "id": "byName",
              "options": "avg"
            },
            "properties": [
              {
                "id": "color",
                "value": {
                  "fixedColor": "semi-dark-green",
                  "mode": "fixed"
                }
              }
            ]
          }
        ]
      },
      "gridPos": {
        "h": 9,
        "w": 12,
        "x": 0,
        "y": 27
      },
      "id": 11,
      "options": {
        "legend": {
          "calcs": ["mean", "max"],
          "displayMode": "list",
          "placement": "bottom"
        },
        "tooltip": {
          "mode": "single",
          "sort": "none"
        }
      },
      "targets": [
        {
          "datasource": {
            "type": "prometheus",
            "uid": "MWzG0Bc4k"
          },
          "editorMode": "code",
          "expr": "avg(rate(container_cpu_usage_seconds_total{namespace=\"army\", container=\"clickhouse\"}[15m]))",
          "legendFormat": "avg",
          "range": true,
          "refId": "A"
        },
        {
          "datasource": {
            "type": "prometheus",
            "uid": "MWzG0Bc4k"
          },
          "editorMode": "code",
          "expr": "max(kube_pod_container_resource_requests{namespace=\"army\", container=\"clickhouse\", resource=\"cpu\"})",
          "hide": false,
          "legendFormat": "request",
          "range": true,
          "refId": "B"
        },
        {
          "datasource": {
            "type": "prometheus",
            "uid": "MWzG0Bc4k"
          },
          "editorMode": "code",
          "expr": "max(kube_pod_container_resource_limits{namespace=\"army\", container=\"clickhouse\", resource=\"cpu\"})",
          "hide": false,
          "legendFormat": "limit",
          "range": true,
          "refId": "C"
        }
      ],
      "title": "CPU usage (clickhouse)",
      "type": "timeseries"
    },
    {
      "datasource": {
        "type": "prometheus",
        "uid": "MWzG0Bc4k"
      },
      "fieldConfig": {
        "defaults": {
          "color": {
            "mode": "palette-classic"
          },
          "custom": {
            "axisLabel": "",
            "axisPlacement": "auto",
            "barAlignment": 0,
            "drawStyle": "line",
            "fillOpacity": 0,
            "gradientMode": "none",
            "hideFrom": {
              "legend": false,
              "tooltip": false,
              "viz": false
            },
            "lineInterpolation": "linear",
            "lineWidth": 1,
            "pointSize": 5,
            "scaleDistribution": {
              "type": "linear"
            },
            "showPoints": "auto",
            "spanNulls": false,
            "stacking": {
              "group": "A",
              "mode": "none"
            },
            "thresholdsStyle": {
              "mode": "off"
            }
          },
          "mappings": [],
          "thresholds": {
            "mode": "absolute",
            "steps": [
              {
                "color": "green"
              },
              {
                "color": "red",
                "value": 80
              }
            ]
          },
          "unit": "bytes"
        },
        "overrides": [
          {
            "matcher": {
              "id": "byName",
              "options": "limit"
            },
            "properties": [
              {
                "id": "color",
                "value": {
                  "fixedColor": "semi-dark-red",
                  "mode": "fixed"
                }
              }
            ]
          },
          {
            "matcher": {
              "id": "byName",
              "options": "request"
            },
            "properties": [
              {
                "id": "color",
                "value": {
                  "fixedColor": "semi-dark-orange",
                  "mode": "fixed"
                }
              }
            ]
          },
          {
            "matcher": {
              "id": "byName",
              "options": "avg"
            },
            "properties": [
              {
                "id": "color",
                "value": {
                  "fixedColor": "semi-dark-green",
                  "mode": "fixed"
                }
              }
            ]
          }
        ]
      },
      "gridPos": {
        "h": 9,
        "w": 12,
        "x": 12,
        "y": 27
      },
      "id": 13,
      "options": {
        "legend": {
          "calcs": ["mean", "max"],
          "displayMode": "list",
          "placement": "bottom"
        },
        "tooltip": {
          "mode": "single",
          "sort": "none"
        }
      },
      "targets": [
        {
          "datasource": {
            "type": "prometheus",
            "uid": "MWzG0Bc4k"
          },
          "editorMode": "code",
          "expr": "avg(container_memory_usage_bytes{namespace=\"army\", container=\"clickhouse\"})",
          "legendFormat": "avg",
          "range": true,
          "refId": "A"
        },
        {
          "datasource": {
            "type": "prometheus",
            "uid": "MWzG0Bc4k"
          },
          "editorMode": "code",
          "expr": "max(kube_pod_container_resource_requests{namespace=\"army\", container=\"clickhouse\", resource=\"memory\"})",
          "hide": false,
          "legendFormat": "request",
          "range": true,
          "refId": "B"
        },
        {
          "datasource": {
            "type": "prometheus",
            "uid": "MWzG0Bc4k"
          },
          "editorMode": "code",
          "expr": "max(kube_pod_container_resource_limits{namespace=\"army\", container=\"clickhouse\", resource=\"memory\"})",
          "hide": false,
          "legendFormat": "limit",
          "range": true,
          "refId": "C"
        }
      ],
      "title": "Memory usage (clickhouse)",
      "type": "timeseries"
    },
    {
      "datasource": {
        "type": "prometheus",
        "uid": "MWzG0Bc4k"
      },
      "fieldConfig": {
        "defaults": {
          "color": {
            "mode": "palette-classic"
          },
          "custom": {
            "axisLabel": "",
            "axisPlacement": "auto",
            "barAlignment": 0,
            "drawStyle": "line",
            "fillOpacity": 0,
            "gradientMode": "none",
            "hideFrom": {
              "legend": false,
              "tooltip": false,
              "viz": false
            },
            "lineInterpolation": "linear",
            "lineWidth": 1,
            "pointSize": 5,
            "scaleDistribution": {
              "type": "linear"
            },
            "showPoints": "auto",
            "spanNulls": false,
            "stacking": {
              "group": "A",
              "mode": "none"
            },
            "thresholdsStyle": {
              "mode": "off"
            }
          },
          "mappings": [],
          "thresholds": {
            "mode": "absolute",
            "steps": [
              {
                "color": "green"
              },
              {
                "color": "red",
                "value": 80
              }
            ]
          },
          "unit": "percentunit"
        },
        "overrides": [
          {
            "matcher": {
              "id": "byName",
              "options": "limit"
            },
            "properties": [
              {
                "id": "color",
                "value": {
                  "fixedColor": "semi-dark-red",
                  "mode": "fixed"
                }
              }
            ]
          },
          {
            "matcher": {
              "id": "byName",
              "options": "request"
            },
            "properties": [
              {
                "id": "color",
                "value": {
                  "fixedColor": "semi-dark-orange",
                  "mode": "fixed"
                }
              }
            ]
          },
          {
            "matcher": {
              "id": "byName",
              "options": "avg"
            },
            "properties": [
              {
                "id": "color",
                "value": {
                  "fixedColor": "semi-dark-green",
                  "mode": "fixed"
                }
              }
            ]
          }
        ]
      },
      "gridPos": {
        "h": 9,
        "w": 12,
        "x": 0,
        "y": 36
      },
      "id": 12,
      "options": {
        "legend": {
          "calcs": ["mean", "max"],
          "displayMode": "list",
          "placement": "bottom"
        },
        "tooltip": {
          "mode": "single",
          "sort": "none"
        }
      },
      "targets": [
        {
          "datasource": {
            "type": "prometheus",
            "uid": "MWzG0Bc4k"
          },
          "editorMode": "code",
          "expr": "avg(rate(container_cpu_usage_seconds_total{namespace=\"army\", container=\"staticmap-api\"}[15m]))",
          "legendFormat": "avg",
          "range": true,
          "refId": "A"
        },
        {
          "datasource": {
            "type": "prometheus",
            "uid": "MWzG0Bc4k"
          },
          "editorMode": "code",
          "expr": "max(kube_pod_container_resource_requests{namespace=\"army\", container=\"staticmap-api\", resource=\"cpu\"})",
          "hide": false,
          "legendFormat": "request",
          "range": true,
          "refId": "B"
        },
        {
          "datasource": {
            "type": "prometheus",
            "uid": "MWzG0Bc4k"
          },
          "editorMode": "code",
          "expr": "max(kube_pod_container_resource_limits{namespace=\"army\", container=\"staticmap-api\", resource=\"cpu\"})",
          "hide": false,
          "legendFormat": "limit",
          "range": true,
          "refId": "C"
        }
      ],
      "title": "CPU usage (staticmap-api)",
      "type": "timeseries"
    },
    {
      "datasource": {
        "type": "prometheus",
        "uid": "MWzG0Bc4k"
      },
      "fieldConfig": {
        "defaults": {
          "color": {
            "mode": "palette-classic"
          },
          "custom": {
            "axisLabel": "",
            "axisPlacement": "auto",
            "barAlignment": 0,
            "drawStyle": "line",
            "fillOpacity": 0,
            "gradientMode": "none",
            "hideFrom": {
              "legend": false,
              "tooltip": false,
              "viz": false
            },
            "lineInterpolation": "linear",
            "lineWidth": 1,
            "pointSize": 5,
            "scaleDistribution": {
              "type": "linear"
            },
            "showPoints": "auto",
            "spanNulls": false,
            "stacking": {
              "group": "A",
              "mode": "none"
            },
            "thresholdsStyle": {
              "mode": "off"
            }
          },
          "mappings": [],
          "thresholds": {
            "mode": "absolute",
            "steps": [
              {
                "color": "green"
              },
              {
                "color": "red",
                "value": 80
              }
            ]
          },
          "unit": "bytes"
        },
        "overrides": [
          {
            "matcher": {
              "id": "byName",
              "options": "limit"
            },
            "properties": [
              {
                "id": "color",
                "value": {
                  "fixedColor": "semi-dark-red",
                  "mode": "fixed"
                }
              }
            ]
          },
          {
            "matcher": {
              "id": "byName",
              "options": "request"
            },
            "properties": [
              {
                "id": "color",
                "value": {
                  "fixedColor": "semi-dark-orange",
                  "mode": "fixed"
                }
              }
            ]
          },
          {
            "matcher": {
              "id": "byName",
              "options": "avg"
            },
            "properties": [
              {
                "id": "color",
                "value": {
                  "fixedColor": "semi-dark-green",
                  "mode": "fixed"
                }
              }
            ]
          }
        ]
      },
      "gridPos": {
        "h": 9,
        "w": 12,
        "x": 12,
        "y": 36
      },
      "id": 14,
      "options": {
        "legend": {
          "calcs": ["mean", "max"],
          "displayMode": "list",
          "placement": "bottom"
        },
        "tooltip": {
          "mode": "single",
          "sort": "none"
        }
      },
      "targets": [
        {
          "datasource": {
            "type": "prometheus",
            "uid": "MWzG0Bc4k"
          },
          "editorMode": "code",
          "expr": "avg(container_memory_usage_bytes{namespace=\"army\", container=\"staticmap-api\"})",
          "legendFormat": "avg",
          "range": true,
          "refId": "A"
        },
        {
          "datasource": {
            "type": "prometheus",
            "uid": "MWzG0Bc4k"
          },
          "editorMode": "code",
          "expr": "max(kube_pod_container_resource_requests{namespace=\"army\", container=\"staticmap-api\", resource=\"memory\"})",
          "hide": false,
          "legendFormat": "request",
          "range": true,
          "refId": "B"
        },
        {
          "datasource": {
            "type": "prometheus",
            "uid": "MWzG0Bc4k"
          },
          "editorMode": "code",
          "expr": "max(kube_pod_container_resource_limits{namespace=\"army\", container=\"staticmap-api\", resource=\"memory\"})",
          "hide": false,
          "legendFormat": "limit",
          "range": true,
          "refId": "C"
        }
      ],
      "title": "Memory usage (static-map)",
      "type": "timeseries"
    },
    {
      "gridPos": {
        "h": 1,
        "w": 24,
        "x": 0,
        "y": 45
      },
      "id": 28,
      "title": "ships-finder",
      "type": "row"
    },
    {
      "datasource": {
        "type": "prometheus",
        "uid": "MWzG0Bc4k"
      },
      "description": "",
      "fieldConfig": {
        "defaults": {
          "color": {
            "mode": "thresholds"
          },
          "mappings": [],
          "min": 0,
          "thresholds": {
            "mode": "absolute",
            "steps": [
              {
                "color": "green"
              },
              {
                "color": "red",
                "value": 80
              }
            ]
          }
        },
        "overrides": []
      },
      "gridPos": {
        "h": 4,
        "w": 3,
        "x": 0,
        "y": 46
      },
      "id": 30,
      "options": {
        "colorMode": "value",
        "graphMode": "area",
        "justifyMode": "center",
        "orientation": "auto",
        "reduceOptions": {
          "calcs": ["lastNotNull"],
          "fields": "",
          "values": false
        },
        "text": {},
        "textMode": "auto"
      },
      "pluginVersion": "9.0.4",
      "targets": [
        {
          "datasource": {
            "type": "prometheus",
            "uid": "lcLUGe74z"
          },
          "editorMode": "code",
          "exemplar": true,
          "expr": "sum(kube_deployment_spec_replicas{namespace='army', deployment=\"ships-finder\"})",
          "interval": "",
          "legendFormat": "",
          "range": true,
          "refId": "A"
        }
      ],
      "title": "Count pod(ships-finder)",
      "type": "stat"
    },
    {
      "datasource": {
        "type": "prometheus",
        "uid": "MWzG0Bc4k"
      },
      "fieldConfig": {
        "defaults": {
          "color": {
            "mode": "palette-classic"
          },
          "custom": {
            "axisLabel": "",
            "axisPlacement": "auto",
            "barAlignment": 0,
            "drawStyle": "line",
            "fillOpacity": 4,
            "gradientMode": "none",
            "hideFrom": {
              "legend": false,
              "tooltip": false,
              "viz": false
            },
            "lineInterpolation": "linear",
            "lineWidth": 1,
            "pointSize": 5,
            "scaleDistribution": {
              "type": "linear"
            },
            "showPoints": "auto",
            "spanNulls": true,
            "stacking": {
              "group": "A",
              "mode": "none"
            },
            "thresholdsStyle": {
              "mode": "off"
            }
          },
          "mappings": [],
          "thresholds": {
            "mode": "absolute",
            "steps": [
              {
                "color": "green"
              },
              {
                "color": "red",
                "value": 80
              }
            ]
          },
          "unit": "s"
        },
        "overrides": []
      },
      "gridPos": {
        "h": 7,
        "w": 10,
        "x": 3,
        "y": 46
      },
      "id": 31,
      "options": {
        "legend": {
          "calcs": ["mean", "max"],
          "displayMode": "table",
          "placement": "bottom"
        },
        "tooltip": {
          "mode": "single",
          "sort": "none"
        }
      },
      "targets": [
        {
          "datasource": {
            "type": "prometheus",
            "uid": "MWzG0Bc4k"
          },
          "editorMode": "code",
          "expr": "histogram_quantile(0.99, sum(rate(ships_finder_http_request_duration_seconds_bucket[15m])) by (le))",
          "legendFormat": "0.99",
          "range": true,
          "refId": "A"
        },
        {
          "datasource": {
            "type": "prometheus",
            "uid": "MWzG0Bc4k"
          },
          "editorMode": "code",
          "expr": "histogram_quantile(0.95, sum(rate(ships_finder_http_request_duration_seconds_bucket[15m])) by (le))",
          "hide": false,
          "legendFormat": "0.95",
          "range": true,
          "refId": "B"
        },
        {
          "datasource": {
            "type": "prometheus",
            "uid": "MWzG0Bc4k"
          },
          "editorMode": "code",
          "expr": "histogram_quantile(0.5, sum(rate(ships_finder_http_request_duration_seconds_bucket[15m])) by (le))",
          "hide": false,
          "legendFormat": "0.5",
          "range": true,
          "refId": "C"
        }
      ],
      "title": "ships_finder_http_request_duration",
      "type": "timeseries"
    },
    {
      "datasource": {
        "type": "prometheus",
        "uid": "MWzG0Bc4k"
      },
      "fieldConfig": {
        "defaults": {
          "color": {
            "mode": "palette-classic"
          },
          "custom": {
            "axisLabel": "",
            "axisPlacement": "auto",
            "barAlignment": 0,
            "drawStyle": "line",
            "fillOpacity": 0,
            "gradientMode": "none",
            "hideFrom": {
              "legend": false,
              "tooltip": false,
              "viz": false
            },
            "lineInterpolation": "linear",
            "lineWidth": 1,
            "pointSize": 5,
            "scaleDistribution": {
              "type": "linear"
            },
            "showPoints": "auto",
            "spanNulls": false,
            "stacking": {
              "group": "A",
              "mode": "none"
            },
            "thresholdsStyle": {
              "mode": "off"
            }
          },
          "mappings": [],
          "thresholds": {
            "mode": "absolute",
            "steps": [
              {
                "color": "green"
              },
              {
                "color": "red",
                "value": 80
              }
            ]
          },
          "unit": "percentunit"
        },
        "overrides": [
          {
            "matcher": {
              "id": "byName",
              "options": "limit"
            },
            "properties": [
              {
                "id": "color",
                "value": {
                  "fixedColor": "semi-dark-red",
                  "mode": "fixed"
                }
              }
            ]
          },
          {
            "matcher": {
              "id": "byName",
              "options": "request"
            },
            "properties": [
              {
                "id": "color",
                "value": {
                  "fixedColor": "semi-dark-orange",
                  "mode": "fixed"
                }
              }
            ]
          },
          {
            "matcher": {
              "id": "byName",
              "options": "avg"
            },
            "properties": [
              {
                "id": "color",
                "value": {
                  "fixedColor": "semi-dark-green",
                  "mode": "fixed"
                }
              }
            ]
          }
        ]
      },
      "gridPos": {
        "h": 7,
        "w": 11,
        "x": 13,
        "y": 46
      },
      "id": 5,
      "options": {
        "legend": {
          "calcs": ["mean", "max"],
          "displayMode": "list",
          "placement": "bottom"
        },
        "tooltip": {
          "mode": "single",
          "sort": "none"
        }
      },
      "targets": [
        {
          "datasource": {
            "type": "prometheus",
            "uid": "MWzG0Bc4k"
          },
          "editorMode": "code",
          "expr": "avg(rate(container_cpu_usage_seconds_total{namespace=\"army\", container=\"ships-finder\"}[15m]))",
          "legendFormat": "avg",
          "range": true,
          "refId": "A"
        },
        {
          "datasource": {
            "type": "prometheus",
            "uid": "MWzG0Bc4k"
          },
          "editorMode": "code",
          "expr": "max(kube_pod_container_resource_requests{namespace=\"army\", container=\"ships-finder\", resource=\"cpu\"})",
          "hide": false,
          "legendFormat": "request",
          "range": true,
          "refId": "B"
        },
        {
          "datasource": {
            "type": "prometheus",
            "uid": "MWzG0Bc4k"
          },
          "editorMode": "code",
          "expr": "max(kube_pod_container_resource_limits{namespace=\"army\", container=\"ships-finder\", resource=\"cpu\"})",
          "hide": false,
          "legendFormat": "limit",
          "range": true,
          "refId": "C"
        }
      ],
      "title": "CPU usage (ships-finder)",
      "type": "timeseries"
    },
    {
      "datasource": {
        "type": "prometheus",
        "uid": "MWzG0Bc4k"
      },
      "description": "",
      "fieldConfig": {
        "defaults": {
          "color": {
            "mode": "thresholds"
          },
          "mappings": [],
          "min": 0,
          "thresholds": {
            "mode": "absolute",
            "steps": [
              {
                "color": "green"
              },
              {
                "color": "red",
                "value": 80
              }
            ]
          }
        },
        "overrides": []
      },
      "gridPos": {
        "h": 4,
        "w": 3,
        "x": 0,
        "y": 50
      },
      "id": 29,
      "options": {
        "colorMode": "value",
        "graphMode": "area",
        "justifyMode": "auto",
        "orientation": "auto",
        "reduceOptions": {
          "calcs": ["lastNotNull"],
          "fields": "",
          "values": false
        },
        "text": {},
        "textMode": "auto"
      },
      "pluginVersion": "9.0.4",
      "targets": [
        {
          "datasource": {
            "type": "prometheus",
            "uid": "lcLUGe74z"
          },
          "editorMode": "code",
          "exemplar": true,
          "expr": "sum(rate(kube_pod_container_status_restarts_total{namespace='army', pod=~\"ships-finder-.{8,10}-.{5}\"}[15m]))",
          "interval": "",
          "legendFormat": "",
          "range": true,
          "refId": "A"
        }
      ],
      "title": "Restart pod(ships-finder)",
      "type": "stat"
    },
    {
      "datasource": {
        "type": "prometheus",
        "uid": "MWzG0Bc4k"
      },
      "description": "",
      "fieldConfig": {
        "defaults": {
          "color": {
            "mode": "palette-classic"
          },
          "custom": {
            "axisLabel": "",
            "axisPlacement": "auto",
            "barAlignment": 0,
            "drawStyle": "line",
            "fillOpacity": 0,
            "gradientMode": "none",
            "hideFrom": {
              "legend": false,
              "tooltip": false,
              "viz": false
            },
            "lineInterpolation": "linear",
            "lineWidth": 1,
            "pointSize": 5,
            "scaleDistribution": {
              "type": "linear"
            },
            "showPoints": "auto",
            "spanNulls": false,
            "stacking": {
              "group": "A",
              "mode": "none"
            },
            "thresholdsStyle": {
              "mode": "off"
            }
          },
          "mappings": [],
          "thresholds": {
            "mode": "absolute",
            "steps": [
              {
                "color": "green"
              },
              {
                "color": "red",
                "value": 80
              }
            ]
          }
        },
        "overrides": []
      },
      "gridPos": {
        "h": 7,
        "w": 10,
        "x": 3,
        "y": 53
      },
      "id": 32,
      "options": {
        "legend": {
          "calcs": [],
          "displayMode": "list",
          "placement": "bottom"
        },
        "tooltip": {
          "mode": "single",
          "sort": "none"
        }
      },
      "targets": [
        {
          "datasource": {
            "type": "prometheus",
            "uid": "MWzG0Bc4k"
          },
          "editorMode": "code",
          "expr": "sum(increase(ships_finder_http_request_duration_seconds_count{code=~'2..'}[24h]))",
          "legendFormat": "200",
          "range": true,
          "refId": "A"
        },
        {
          "datasource": {
            "type": "prometheus",
            "uid": "MWzG0Bc4k"
          },
          "expr": "sum(rate(ships_finder_http_request_duration_seconds_count{code=~'4..'}[15m]))",
          "hide": false,
          "refId": "B"
        },
        {
          "datasource": {
            "type": "prometheus",
            "uid": "MWzG0Bc4k"
          },
          "expr": "sum(rate(ships_finder_http_request_duration_seconds_count{code=~'5..'}[15m]))",
          "hide": false,
          "refId": "C"
        }
      ],
      "title": "ships_finder_http_request_count by code",
      "type": "timeseries"
    },
    {
      "datasource": {
        "type": "prometheus",
        "uid": "MWzG0Bc4k"
      },
      "fieldConfig": {
        "defaults": {
          "color": {
            "mode": "palette-classic"
          },
          "custom": {
            "axisLabel": "",
            "axisPlacement": "auto",
            "barAlignment": 0,
            "drawStyle": "line",
            "fillOpacity": 0,
            "gradientMode": "none",
            "hideFrom": {
              "legend": false,
              "tooltip": false,
              "viz": false
            },
            "lineInterpolation": "linear",
            "lineWidth": 1,
            "pointSize": 5,
            "scaleDistribution": {
              "type": "linear"
            },
            "showPoints": "auto",
            "spanNulls": false,
            "stacking": {
              "group": "A",
              "mode": "none"
            },
            "thresholdsStyle": {
              "mode": "off"
            }
          },
          "mappings": [],
          "thresholds": {
            "mode": "absolute",
            "steps": [
              {
                "color": "green"
              },
              {
                "color": "red",
                "value": 80
              }
            ]
          },
          "unit": "bytes"
        },
        "overrides": [
          {
            "matcher": {
              "id": "byName",
              "options": "limit"
            },
            "properties": [
              {
                "id": "color",
                "value": {
                  "fixedColor": "semi-dark-red",
                  "mode": "fixed"
                }
              }
            ]
          },
          {
            "matcher": {
              "id": "byName",
              "options": "request"
            },
            "properties": [
              {
                "id": "color",
                "value": {
                  "fixedColor": "semi-dark-orange",
                  "mode": "fixed"
                }
              }
            ]
          },
          {
            "matcher": {
              "id": "byName",
              "options": "avg"
            },
            "properties": [
              {
                "id": "color",
                "value": {
                  "fixedColor": "semi-dark-green",
                  "mode": "fixed"
                }
              }
            ]
          }
        ]
      },
      "gridPos": {
        "h": 7,
        "w": 11,
        "x": 13,
        "y": 53
      },
      "id": 6,
      "options": {
        "legend": {
          "calcs": ["mean", "max"],
          "displayMode": "list",
          "placement": "bottom"
        },
        "tooltip": {
          "mode": "single",
          "sort": "none"
        }
      },
      "targets": [
        {
          "datasource": {
            "type": "prometheus",
            "uid": "MWzG0Bc4k"
          },
          "editorMode": "code",
          "expr": "avg(container_memory_usage_bytes{namespace=\"army\", container=\"ships-finder\"})",
          "legendFormat": "avg",
          "range": true,
          "refId": "A"
        },
        {
          "datasource": {
            "type": "prometheus",
            "uid": "MWzG0Bc4k"
          },
          "editorMode": "code",
          "expr": "max(kube_pod_container_resource_requests{namespace=\"army\", container=\"ships-finder\", resource=\"memory\"})",
          "hide": false,
          "legendFormat": "request",
          "range": true,
          "refId": "B"
        },
        {
          "datasource": {
            "type": "prometheus",
            "uid": "MWzG0Bc4k"
          },
          "editorMode": "code",
          "expr": "max(kube_pod_container_resource_limits{namespace=\"army\", container=\"ships-finder\", resource=\"memory\"})",
          "hide": false,
          "legendFormat": "limit",
          "range": true,
          "refId": "C"
        }
      ],
      "title": "Memory usage (ships-finder)",
      "type": "timeseries"
    },
    {
      "collapsed": false,
      "gridPos": {
        "h": 1,
        "w": 24,
        "x": 0,
        "y": 60
      },
      "id": 24,
      "panels": [],
      "title": "notams-bot",
      "type": "row"
    },
    {
      "datasource": {},
      "description": "",
      "fieldConfig": {
        "defaults": {
          "color": {
            "mode": "thresholds"
          },
          "mappings": [],
          "min": 0,
          "thresholds": {
            "mode": "absolute",
            "steps": [
              {
                "color": "green"
              },
              {
                "color": "red",
                "value": 80
              }
            ]
          }
        },
        "overrides": []
      },
      "gridPos": {
        "h": 4,
        "w": 3,
        "x": 0,
        "y": 61
      },
      "id": 18,
      "options": {
        "colorMode": "value",
        "graphMode": "area",
        "justifyMode": "center",
        "orientation": "auto",
        "reduceOptions": {
          "calcs": ["lastNotNull"],
          "fields": "",
          "values": false
        },
        "text": {},
        "textMode": "auto"
      },
      "pluginVersion": "9.0.4",
      "targets": [
        {
          "datasource": {
            "type": "prometheus",
            "uid": "lcLUGe74z"
          },
          "editorMode": "code",
          "exemplar": true,
          "expr": "sum(kube_deployment_spec_replicas{namespace='army', deployment=\"notams-bot\"})",
          "interval": "",
          "legendFormat": "",
          "range": true,
          "refId": "A"
        }
      ],
      "title": "Count pod(notams-bot)",
      "type": "stat"
    },
    {
      "datasource": {
        "type": "prometheus",
        "uid": "MWzG0Bc4k"
      },
      "fieldConfig": {
        "defaults": {
          "color": {
            "mode": "palette-classic"
          },
          "custom": {
            "axisLabel": "",
            "axisPlacement": "auto",
            "barAlignment": 0,
            "drawStyle": "line",
            "fillOpacity": 4,
            "gradientMode": "none",
            "hideFrom": {
              "legend": false,
              "tooltip": false,
              "viz": false
            },
            "lineInterpolation": "linear",
            "lineWidth": 1,
            "pointSize": 5,
            "scaleDistribution": {
              "type": "linear"
            },
            "showPoints": "auto",
            "spanNulls": true,
            "stacking": {
              "group": "A",
              "mode": "none"
            },
            "thresholdsStyle": {
              "mode": "off"
            }
          },
          "mappings": [],
          "thresholds": {
            "mode": "absolute",
            "steps": [
              {
                "color": "green"
              },
              {
                "color": "red",
                "value": 80
              }
            ]
          },
          "unit": "s"
        },
        "overrides": []
      },
      "gridPos": {
        "h": 7,
        "w": 10,
        "x": 3,
        "y": 61
      },
      "id": 22,
      "options": {
        "legend": {
          "calcs": ["mean", "max"],
          "displayMode": "table",
          "placement": "bottom"
        },
        "tooltip": {
          "mode": "single",
          "sort": "none"
        }
      },
      "targets": [
        {
          "datasource": {
            "type": "prometheus",
            "uid": "MWzG0Bc4k"
          },
          "editorMode": "code",
          "expr": "histogram_quantile(0.99, sum(rate(notams_bot_http_request_duration_seconds_bucket{pod=~\"notams-bot-.{9,10}-.{5}\"}[15m])) by (le))",
          "legendFormat": "0.99",
          "range": true,
          "refId": "A"
        },
        {
          "datasource": {
            "type": "prometheus",
            "uid": "MWzG0Bc4k"
          },
          "editorMode": "code",
          "expr": "histogram_quantile(0.95, sum(rate(notams_bot_http_request_duration_seconds_bucket{pod=~\"notams-bot-.{9,10}-.{5}\"}[15m])) by (le))",
          "hide": false,
          "legendFormat": "0.95",
          "range": true,
          "refId": "B"
        },
        {
          "datasource": {
            "type": "prometheus",
            "uid": "MWzG0Bc4k"
          },
          "editorMode": "code",
          "expr": "histogram_quantile(0.5, sum(rate(notams_bot_http_request_duration_seconds_bucket{pod=~\"notams-bot-.{9,10}-.{5}\"}[15m])) by (le))",
          "hide": false,
          "legendFormat": "0.5",
          "range": true,
          "refId": "C"
        }
      ],
      "title": "notams_bot_http_request_duration",
      "type": "timeseries"
    },
    {
      "datasource": {
        "type": "prometheus",
        "uid": "MWzG0Bc4k"
      },
      "fieldConfig": {
        "defaults": {
          "color": {
            "mode": "palette-classic"
          },
          "custom": {
            "axisLabel": "",
            "axisPlacement": "auto",
            "barAlignment": 0,
            "drawStyle": "line",
            "fillOpacity": 0,
            "gradientMode": "none",
            "hideFrom": {
              "legend": false,
              "tooltip": false,
              "viz": false
            },
            "lineInterpolation": "linear",
            "lineWidth": 1,
            "pointSize": 5,
            "scaleDistribution": {
              "type": "linear"
            },
            "showPoints": "auto",
            "spanNulls": false,
            "stacking": {
              "group": "A",
              "mode": "none"
            },
            "thresholdsStyle": {
              "mode": "off"
            }
          },
          "mappings": [],
          "thresholds": {
            "mode": "absolute",
            "steps": [
              {
                "color": "green"
              },
              {
                "color": "red",
                "value": 80
              }
            ]
          },
          "unit": "percentunit"
        },
        "overrides": [
          {
            "matcher": {
              "id": "byName",
              "options": "limit"
            },
            "properties": [
              {
                "id": "color",
                "value": {
                  "fixedColor": "semi-dark-red",
                  "mode": "fixed"
                }
              }
            ]
          },
          {
            "matcher": {
              "id": "byName",
              "options": "request"
            },
            "properties": [
              {
                "id": "color",
                "value": {
                  "fixedColor": "semi-dark-orange",
                  "mode": "fixed"
                }
              }
            ]
          },
          {
            "matcher": {
              "id": "byName",
              "options": "avg"
            },
            "properties": [
              {
                "id": "color",
                "value": {
                  "fixedColor": "semi-dark-green",
                  "mode": "fixed"
                }
              }
            ]
          }
        ]
      },
      "gridPos": {
        "h": 7,
        "w": 11,
        "x": 13,
        "y": 61
      },
      "id": 4,
      "options": {
        "legend": {
          "calcs": ["mean", "max"],
          "displayMode": "list",
          "placement": "bottom"
        },
        "tooltip": {
          "mode": "single",
          "sort": "none"
        }
      },
      "targets": [
        {
          "datasource": {
            "type": "prometheus",
            "uid": "MWzG0Bc4k"
          },
          "editorMode": "code",
          "expr": "avg(rate(container_cpu_usage_seconds_total{namespace=\"army\", container=\"notams-bot\"}[15m]))",
          "legendFormat": "avg",
          "range": true,
          "refId": "A"
        },
        {
          "datasource": {
            "type": "prometheus",
            "uid": "MWzG0Bc4k"
          },
          "editorMode": "code",
          "expr": "max(kube_pod_container_resource_requests{namespace=\"army\", container=\"notams-bot\", resource=\"cpu\"})",
          "hide": false,
          "legendFormat": "request",
          "range": true,
          "refId": "B"
        },
        {
          "datasource": {
            "type": "prometheus",
            "uid": "MWzG0Bc4k"
          },
          "editorMode": "code",
          "expr": "max(kube_pod_container_resource_limits{namespace=\"army\", container=\"notams-bot\", resource=\"cpu\"})",
          "hide": false,
          "legendFormat": "limit",
          "range": true,
          "refId": "C"
        }
      ],
      "title": "CPU usage (notams-bot)",
      "type": "timeseries"
    },
    {
      "datasource": {},
      "description": "",
      "fieldConfig": {
        "defaults": {
          "color": {
            "mode": "thresholds"
          },
          "mappings": [],
          "min": 0,
          "thresholds": {
            "mode": "absolute",
            "steps": [
              {
                "color": "green"
              },
              {
                "color": "red",
                "value": 80
              }
            ]
          }
        },
        "overrides": []
      },
      "gridPos": {
        "h": 4,
        "w": 3,
        "x": 0,
        "y": 65
      },
      "id": 20,
      "options": {
        "colorMode": "value",
        "graphMode": "area",
        "justifyMode": "auto",
        "orientation": "auto",
        "reduceOptions": {
          "calcs": ["lastNotNull"],
          "fields": "",
          "values": false
        },
        "text": {},
        "textMode": "auto"
      },
      "pluginVersion": "9.0.4",
      "targets": [
        {
          "datasource": {
            "type": "prometheus",
            "uid": "lcLUGe74z"
          },
          "editorMode": "code",
          "exemplar": true,
          "expr": "sum(rate(kube_pod_container_status_restarts_total{namespace='army', pod=~\"notams-bot-.{8,10}-.{5}\"}[15m]))",
          "interval": "",
          "legendFormat": "",
          "range": true,
          "refId": "A"
        }
      ],
      "title": "Restart pod(notams-bot)",
      "type": "stat"
    },
    {
      "datasource": {
        "type": "prometheus",
        "uid": "MWzG0Bc4k"
      },
      "description": "",
      "fieldConfig": {
        "defaults": {
          "color": {
            "mode": "palette-classic"
          },
          "custom": {
            "axisLabel": "",
            "axisPlacement": "auto",
            "barAlignment": 0,
            "drawStyle": "line",
            "fillOpacity": 0,
            "gradientMode": "none",
            "hideFrom": {
              "legend": false,
              "tooltip": false,
              "viz": false
            },
            "lineInterpolation": "linear",
            "lineWidth": 1,
            "pointSize": 5,
            "scaleDistribution": {
              "type": "linear"
            },
            "showPoints": "auto",
            "spanNulls": false,
            "stacking": {
              "group": "A",
              "mode": "none"
            },
            "thresholdsStyle": {
              "mode": "off"
            }
          },
          "mappings": [],
          "thresholds": {
            "mode": "absolute",
            "steps": [
              {
                "color": "green"
              },
              {
                "color": "red",
                "value": 80
              }
            ]
          }
        },
        "overrides": []
      },
      "gridPos": {
        "h": 7,
        "w": 10,
        "x": 3,
        "y": 68
      },
      "id": 26,
      "options": {
        "legend": {
          "calcs": [],
          "displayMode": "list",
          "placement": "bottom"
        },
        "tooltip": {
          "mode": "single",
          "sort": "none"
        }
      },
      "targets": [
        {
          "datasource": {
            "type": "prometheus",
            "uid": "MWzG0Bc4k"
          },
          "editorMode": "code",
          "expr": "sum(increase(notams_bot_http_request_duration_seconds_count{code=~'2..'}[24h]))",
          "legendFormat": "200",
          "range": true,
          "refId": "A"
        },
        {
          "datasource": {
            "type": "prometheus",
            "uid": "MWzG0Bc4k"
          },
          "expr": "sum(rate(notams_bot_http_request_duration_seconds_count{code=~'4..'}[15m]))",
          "hide": false,
          "refId": "B"
        },
        {
          "datasource": {
            "type": "prometheus",
            "uid": "MWzG0Bc4k"
          },
          "expr": "sum(rate(notams_bot_http_request_duration_seconds_count{code=~'5..'}[15m]))",
          "hide": false,
          "refId": "C"
        }
      ],
      "title": "notams_bot_http_request_count by code",
      "type": "timeseries"
    },
    {
      "datasource": {
        "type": "prometheus",
        "uid": "MWzG0Bc4k"
      },
      "fieldConfig": {
        "defaults": {
          "color": {
            "mode": "palette-classic"
          },
          "custom": {
            "axisLabel": "",
            "axisPlacement": "auto",
            "barAlignment": 0,
            "drawStyle": "line",
            "fillOpacity": 0,
            "gradientMode": "none",
            "hideFrom": {
              "legend": false,
              "tooltip": false,
              "viz": false
            },
            "lineInterpolation": "linear",
            "lineWidth": 1,
            "pointSize": 5,
            "scaleDistribution": {
              "type": "linear"
            },
            "showPoints": "auto",
            "spanNulls": false,
            "stacking": {
              "group": "A",
              "mode": "none"
            },
            "thresholdsStyle": {
              "mode": "off"
            }
          },
          "mappings": [],
          "thresholds": {
            "mode": "absolute",
            "steps": [
              {
                "color": "green"
              },
              {
                "color": "red",
                "value": 80
              }
            ]
          },
          "unit": "bytes"
        },
        "overrides": [
          {
            "matcher": {
              "id": "byName",
              "options": "limit"
            },
            "properties": [
              {
                "id": "color",
                "value": {
                  "fixedColor": "semi-dark-red",
                  "mode": "fixed"
                }
              }
            ]
          },
          {
            "matcher": {
              "id": "byName",
              "options": "request"
            },
            "properties": [
              {
                "id": "color",
                "value": {
                  "fixedColor": "semi-dark-orange",
                  "mode": "fixed"
                }
              }
            ]
          },
          {
            "matcher": {
              "id": "byName",
              "options": "avg"
            },
            "properties": [
              {
                "id": "color",
                "value": {
                  "fixedColor": "semi-dark-green",
                  "mode": "fixed"
                }
              }
            ]
          }
        ]
      },
      "gridPos": {
        "h": 7,
        "w": 11,
        "x": 13,
        "y": 68
      },
      "id": 2,
      "options": {
        "legend": {
          "calcs": ["last"],
          "displayMode": "list",
          "placement": "bottom"
        },
        "tooltip": {
          "mode": "single",
          "sort": "none"
        }
      },
      "targets": [
        {
          "datasource": {
            "type": "prometheus",
            "uid": "MWzG0Bc4k"
          },
          "editorMode": "code",
          "expr": "avg(container_memory_usage_bytes{namespace=\"army\", container=\"notams-bot\"})",
          "legendFormat": "avg",
          "range": true,
          "refId": "A"
        },
        {
          "datasource": {
            "type": "prometheus",
            "uid": "MWzG0Bc4k"
          },
          "editorMode": "code",
          "expr": "max(kube_pod_container_resource_requests{namespace=\"army\", container=\"notams-bot\", resource=\"memory\"})",
          "hide": false,
          "legendFormat": "request",
          "range": true,
          "refId": "B"
        },
        {
          "datasource": {
            "type": "prometheus",
            "uid": "MWzG0Bc4k"
          },
          "editorMode": "code",
          "expr": "max(kube_pod_container_resource_limits{namespace=\"army\", container=\"notams-bot\", resource=\"memory\"})",
          "hide": false,
          "legendFormat": "limit",
          "range": true,
          "refId": "C"
        }
      ],
      "title": "Memory usage (notams-bot)",
      "type": "timeseries"
    }
  ],
  "refresh": "30s",
  "schemaVersion": 36,
  "style": "dark",
  "tags": [],
  "templating": {
    "list": []
  },
  "time": {
    "from": "now-6h",
    "to": "now"
  },
  "timepicker": {},
  "timezone": "",
  "title": "Bots",
  "uid": "yt_UCX54z",
  "version": 14,
  "weekStart": ""
}
